dreamcoat/__init__.py
dreamcoat/convert.py
dreamcoat/ctd.py
dreamcoat/glider.py
dreamcoat/meta.py
dreamcoat/neutral.py
dreamcoat/plot.py
dreamcoat/stats.py
dreamcoat/underway.py
dreamcoat/great_circle_calculator/__conversion.py
dreamcoat/great_circle_calculator/__error_checking.py
dreamcoat/great_circle_calculator/__init__.py
dreamcoat/great_circle_calculator/_constants.py
dreamcoat/great_circle_calculator/compass.py
dreamcoat/great_circle_calculator/great_circle_calculator.py
dreamcoat/maps/__init__.py
dreamcoat/maps/degrees_decimal_minutes.py
dreamcoat/maps/vptree/__init__.py
dreamcoat-0.4.dist-info/LICENSE
dreamcoat-0.4.dist-info/METADATA
dreamcoat-0.4.dist-info/WHEEL
dreamcoat-0.4.dist-info/top_level.txt
dreamcoat-0.4.dist-info/RECORD
